pytest_json_fixtures.py
pytest_json_fixtures-0.2.0.dist-info/LICENSE
pytest_json_fixtures-0.2.0.dist-info/METADATA
pytest_json_fixtures-0.2.0.dist-info/WHEEL
pytest_json_fixtures-0.2.0.dist-info/entry_points.txt
pytest_json_fixtures-0.2.0.dist-info/top_level.txt
pytest_json_fixtures-0.2.0.dist-info/RECORD
