Metadata-Version: 2.1
Name: pytest-json-fixtures
Version: 0.2.0
Summary: JSON output for the --fixtures flag
Home-page: https://github.com/marcosanchotene/pytest-json-fixtures
Author: Marco Sanchotene
Author-email: marco@pontograu.com
Maintainer: Marco Sanchotene
Maintainer-email: marco@pontograu.com
License: MIT
Classifier: Development Status :: 4 - Beta
Classifier: Framework :: Pytest
Classifier: Intended Audience :: Developers
Classifier: Topic :: Software Development :: Testing
Classifier: Programming Language :: Python
Classifier: Programming Language :: Python :: 3
Classifier: Programming Language :: Python :: 3.5
Classifier: Programming Language :: Python :: 3.6
Classifier: Programming Language :: Python :: 3.7
Classifier: Programming Language :: Python :: 3.8
Classifier: Programming Language :: Python :: 3 :: Only
Classifier: Programming Language :: Python :: Implementation :: CPython
Classifier: Programming Language :: Python :: Implementation :: PyPy
Classifier: Operating System :: OS Independent
Classifier: License :: OSI Approved :: MIT License
Requires-Python: >=3.5
License-File: LICENSE
Requires-Dist: pytest (>=7.1.0)
